llmify/__init__.py
llmify/messages.py
llmify/providers/__init__.py
llmify/providers/azure.py
llmify/providers/base.py
llmify/providers/openai.py
llmify/tools/__init__.py
llmify/tools/function.py
llmify/tools/protocol.py
llmify/tools/schema.py
py_llmify-0.1.3.dist-info/licenses/LICENCE
py_llmify-0.1.3.dist-info/METADATA
py_llmify-0.1.3.dist-info/WHEEL
py_llmify-0.1.3.dist-info/top_level.txt
py_llmify-0.1.3.dist-info/RECORD
