Metadata-Version: 2.4
Name: py-llmify
Version: 0.1.3
Summary: A minimal, fast, and type-safe Python library for LLM chat completions with OpenAI and Azure OpenAI support
Requires-Python: >=3.11
License-File: LICENCE
Requires-Dist: openai>=2.14.0
Requires-Dist: pydantic>=2.12.5
Requires-Dist: python-dotenv>=1.2.1
Dynamic: license-file
